MANIFEST.in
README.md
pyproject.toml
setup.py
peggie/__init__.py
peggie/error_message_generation.py
peggie/grammar_compiler.py
peggie/meta_grammar.peg
peggie/meta_grammar.py
peggie/parser.py
peggie/py.typed
peggie/transformer.py
peggie/version.py
peggie.egg-info/PKG-INFO
peggie.egg-info/SOURCES.txt
peggie.egg-info/dependency_links.txt
peggie.egg-info/entry_points.txt
peggie.egg-info/not-zip-safe
peggie.egg-info/top_level.txt