Metadata-Version: 1.1
Name: peggie
Version: 0.2.1
Summary: A simple PEG parser with native indentation sensitivity.
Home-page: https://github.com/mossblaser/peggie
Author: BBC R&D
Author-email: UNKNOWN
License: GPL-2.0-or-later
Keywords: PEG parser
Platform: UNKNOWN
Classifier: Development Status :: 3 - Alpha
Classifier: Intended Audience :: Developers
Classifier: License :: OSI Approved :: GNU General Public License v2 (GPLv2)
Classifier: Operating System :: POSIX :: Linux
Classifier: Operating System :: Microsoft :: Windows
Classifier: Operating System :: MacOS
Classifier: Programming Language :: Python :: 3
Classifier: Programming Language :: Python :: 3.7
